metecli/__init__.py
metecli/account.py
metecli/audits.py
metecli/cmdline.py
metecli/config.py
metecli/drinks.py
metecli/main.py
metecli/setup.py
metecli/show_version.py
metecli/utils.py
metecli/connection/__init__.py
metecli/connection/config.py
metecli/connection/connection.py
metecli/connection/apis/__init__.py
metecli/connection/apis/apiv1.py
metecli/connection/apis/apiv2.py
metecli/connection/apis/apiv3.py
metecli/connection/models/__init__.py
metecli/connection/models/audit.py
metecli/connection/models/barcode.py
metecli/connection/models/drink.py
metecli/connection/models/server_info.py
metecli/connection/models/user.py
metecli-0.10.2.dist-info/LICENSE
metecli-0.10.2.dist-info/METADATA
metecli-0.10.2.dist-info/WHEEL
metecli-0.10.2.dist-info/entry_points.txt
metecli-0.10.2.dist-info/top_level.txt
metecli-0.10.2.dist-info/RECORD
