Metadata-Version: 2.1
Name: metecli
Version: 0.10.2
Summary: a cli for mete
Home-page: https://github.com/YtvwlD/metecli
Author: Niklas Sombert
Author-email: niklas@ytvwld.de
License: GPLv3
Keywords: mete
Classifier: Development Status :: 3 - Alpha
Classifier: Environment :: Console
Classifier: Intended Audience :: Developers
Classifier: Intended Audience :: End Users/Desktop
Classifier: Natural Language :: English
Classifier: Topic :: Utilities
Classifier: Topic :: Internet
Classifier: License :: OSI Approved :: GNU General Public License v3 (GPLv3)
Classifier: Programming Language :: Python :: 3
Classifier: Programming Language :: Python :: 3.3
Classifier: Programming Language :: Python :: 3.4
Classifier: Programming Language :: Python :: 3.5
Classifier: Programming Language :: Python :: 3.6
Requires-Python: ~=3.3
License-File: LICENSE
Requires-Dist: requests
Requires-Dist: PyYAML
Requires-Dist: tabulate
Requires-Dist: typing
Requires-Dist: interrogatio
